{
  "_id": "6883715f1eef35261f3907d9",
  "content_hash": "034fdd26207765de5c597e9e01d113b0",
  "collected_at": "2025-07-25T12:12:49.606835",
  "content": "740 \n \nKSU        \nKWASU  \nLANDMARK  \nLAPAI  \nLEGACY  \nMC-IBRU  \nMOUNTAIN TOP  \nMAITAMA  \nNOVENA                              \nNTNU  \nOOU                                    \nODUDUWA  \nPAN-ATLANTIC  \nREDEEMERS    \nRENAISSANCE   \nRITMAN  \nSALEM         \nSAU  \nSOUTHWESTERN  \nSUMMIT  \nTANSIAN      \nTSUJ         \nUMUDIKE  \nUMYUK  \nUNIHEZ  \nUNIKINGS  \nVERITAS  \nWESTERN-DEL  \nWESLEYUNI  \nYOSU  \n  \nBUSINESS ADMINISTRATION/  \n   (xviii) CRAWFORD accepts   \na. For Marketing:  \n             i. Two (2) 'A' level passes in Economics or anyone of Business \nManagement, Geography, Accounting Government,  \nMathematics or Statistics.              ii. NCE - With passes in \nAccounting, Business Studies or any  \nSocial Science             iii. ND/HND in relevant subjects not \nlower than Lower Credit.            b. For Accountancy:  \ni. Two (2) 'A' level passes including Economics plus anyone of \nAccounting, Government, Commerce, and Business \nManagement.  \nii. NCE pass in Accounting, Business Studies or any Social  \nScience  \niii. ND/HND lower credit in relevant subjects.           c. For \nBusiness Administration:  \n            i. Two (2) 'A' level passes in Economics and any one (1) of  \n Business  Management,  Geography,  Accounting,  \nGovernment, or Statistics               ii. NCE merit in Business \nManagement or any Social Science subject.  \n             iii. ND/HND lower credit in relevant subjects.  \n(xix) AAU for Public Administration requires two (2) 'A' level \npasses including Government/History, Economics or any \nother Social Science subject.  \n(xx) WESTERN-DEL accepts  \na. For Accounting:  \ni. Two (2) 'A' Level passes including Economics and one (1) other \nsubject.  \nii. NCE merit in relevant subjects.  \niii. ND lower credit in Accounting, Banking and Finance, Business \nAdministration.  Intermediate passes in ICAN, ACCA, ICMA and \nCIBN examinations.  \nb. For Business Administration:  \ni. Two (2) 'A' level passes in Economics and one (1) other Social \nScience subject.  \nii. ND in Accounting, Banking and Finance, Business \nAdministration, Marketing or Insurance, NCE in Business \nStudies.  \n(xxi) AUE:",
  "file_info": {
    "filename": "Jamb-Brochure.pdf",
    "filepath": "/app/processing_data/processing_data/pdf_documents/Jamb-Brochure.pdf",
    "page_number": 762,
    "total_pages": 1307,
    "file_size": 6544653
  },
  "metadata": {
    "producer": "Microsoft\u00ae Word 2016",
    "creator": "Microsoft\u00ae Word 2016",
    "creationdate": "2019-12-12T08:14:27+01:00",
    "author": "Stephen Tamuno-opubo",
    "moddate": "2019-12-12T08:14:27+01:00",
    "source": "/app/processing_data/processing_data/pdf_documents/Jamb-Brochure.pdf",
    "total_pages": 1307,
    "page": 761,
    "page_label": "762"
  },
  "source": "Jamb-Brochure.pdf#page=762",
  "type": "pdf",
  "year": null
}