{
  "_id": "6883715a1eef35261f390523",
  "content_hash": "097e93991d09f584468b727500574a42",
  "collected_at": "2025-07-25T12:14:16.530070",
  "content": "82 \n \nDEGREE AWARDING  \nINSTITUTIONS  \nDIRECT ENTRY  UTME    \nUTME SUBJECTS  \n    Geography, Government, Biology, Chemistry, \nPhysics, Commerce, Civic Education and \nInsurance.  \n(iii) NDU requires five (5) \u2018O\u2019 level credit passes in \nEnglish, Mathematics, Economics, and any \nother two (2) subjects at not more than two  \n(2) sittings.  \n  \n  \nUTME SUBJECTS  \n(i) ABU as in Accountancy.  \n(ii) LAGOS requires Mathematics, Economics and \nany one (1) Subject from Financial \nAccounting, Geography, Government, \nBiology, Chemistry,  \nPhysics and Commerce   \nINTERNATIONAL RELATIONS:  \nOAU  \nWELLSPRING         \n  \n  \nINTERNATIONAL   \nRELATIONS AND   \nSTRATEGIC STUDIES  \nNOVENA   \n  \nINTERNATIONAL   \nSTUDIES AND   \nDIPLOMACY  \nKASU  \n  \nTwo (2) \u2018A\u2019 level passes in \nany of the following \nsubjects: Government, \nEconomics, History and \nFrench.  \n  \nFive (5) SSC credit passes \nincluding English \nLanguage, Government \nand Mathematics and \nany other two (2) \nrelevant subjects.  \n  \nMathematics and any \ntwo (2) of the \nfollowing:   \nEconomics,  History,  \nGovernment,  \nGeography,  \nLiterature in English \nand French.  \n  \nDIRECT ENTRY  \n(i) OAU requires plus two (2) \u2018A\u2019 Level passes in \nGovernment and Economics or History.  \n(ii) WELLSPRING accepts two (2) \u2018A\u2019 Level passes \n(including NABTEB).  \n  \nUTME  \n(i) OAU requires five (5) 'O' Level credit passes \nwhich must include English Language,  \nMathematics, Government and two (2) other \nsubjects  from \nHistory/Economics/Geography/Literature in \nEnglish.  \n(ii) WELLSPRING accepts a pass in Mathematics \nprovided the candidate has a total of five (5) \n\u2018O\u2019 level credit passes including English \nlanguage, Govern ment/History, and \nEconomics  \n  \nUTME SUBJECTS",
  "file_info": {
    "filename": "Jamb-Brochure.pdf",
    "filepath": "/app/processing_data/processing_data/pdf_documents/Jamb-Brochure.pdf",
    "page_number": 104,
    "total_pages": 1307,
    "file_size": 6544653
  },
  "metadata": {
    "producer": "Microsoft\u00ae Word 2016",
    "creator": "Microsoft\u00ae Word 2016",
    "creationdate": "2019-12-12T08:14:27+01:00",
    "author": "Stephen Tamuno-opubo",
    "moddate": "2019-12-12T08:14:27+01:00",
    "source": "/app/processing_data/processing_data/pdf_documents/Jamb-Brochure.pdf",
    "total_pages": 1307,
    "page": 103,
    "page_label": "104"
  },
  "source": "Jamb-Brochure.pdf#page=104",
  "type": "pdf",
  "year": null
}