{
  "_id": "6883715f1eef35261f3907a5",
  "content_hash": "1d188a1bd18fecd23953c9295995564d",
  "collected_at": "2025-07-25T12:59:36.492694",
  "content": "696 \n \nPROGRAMME/DEGREE  \nAWARDING INSTITUTIONS  \nREQUIREMENTS  \n  \n  \n  \n  \nUTME SUBJECTS  \nSPECIAL CONSIDERATION (WAIVER) REMARKS  \nDIRECT ENTRY  UTME  \nMKAR       \nMOUNTAIN TOP  \nNASARAWA                   \nNDU  \nNOVENA     \nNTNU  \nOAU      \nOBONG  \nODUDUWA                          \nOOU  \nOSUMS            \nOSUSTECH  \nPHC  \nPLASU       \nREDEEMERS   \nRENAISSANCE   \nRHEMA  \nSAU  \nSOSU  \nSOUTHWESTERN  \nSUMMIT  \nTANSIAN  \nTECH-IBADAN  \nUDU       \nUMUDIKE     \nUMYUK  \nUNIKINGS  \nUNIOSUN  \nUNN       \n   (xxxv) CALEB accepts ND credit in Science Laboratory Technology \nor Sciences related programmes for admission by direct \nentry provided they have the UTME subjects at one (1) \nsitting.  \n(xxxvi) CUAB accepts IJMB and 'A' level passes in Mathematics,  \nChemistry, Physics or Ge ography at acceptable grades. (ii)  \nND, HND or its equivalent in Agricultural Science or Civil \nEngineering or related programmes provided the  UTME  \nrequirements have been met can be admitted into 200  \nlevel.  \n(xxxvii) BSU for Environmental Management and Toxicolog y \naccepts ND/HND upper credit in Health Technology, \nAgriculture and other related programme.  \n(xxxviii) UMYUK requires (2) 'A' level passes from Biology, \nChemistry, Biochemistry etc. Candidates must have 'A' \nlevel Biology. NCE candidates must have Biology and \nChemistry.  \n(xxxix) SOUTHWESTERN accepts  \na. NCE credit in Biology or Chemistry. 'A' level passes in \nChemistry and Biology/Botany/Zoology.  \nb. Accepts ND upper credit or HND in relevant programmes  'O' \nlevel credit passes in either Physics or Mathematics in \naddition to 'A' level passes in Chemistry and Biology is \nacceptable.  \n(lx)  BENIN for Science Laboratory Technology in addition to \nthe UTME requirements may accept  two (2) 'A' level passes  or \nits recognized equivalents at not more than two (2) sittings.   \nThe subjects should be of the Sciences.  \n(xli) BAUCHI accepts IJMB/A level/ passes in Biology, Chemistry and \nanyone of Mathematics, Physics or Agricultural Science. ND  \nlower credit in the following areas: Science Laboratory  \nTechnology and Food Science Technology. The candidate \nmust also have the five (5) 'O' level credit passes in English \nLanguage, Mathematics, Chemistry, Biology and Physics.",
  "file_info": {
    "filename": "Jamb-Brochure.pdf",
    "filepath": "/app/processing_data/processing_data/pdf_documents/Jamb-Brochure.pdf",
    "page_number": 718,
    "total_pages": 1307,
    "file_size": 6544653
  },
  "metadata": {
    "producer": "Microsoft\u00ae Word 2016",
    "creator": "Microsoft\u00ae Word 2016",
    "creationdate": "2019-12-12T08:14:27+01:00",
    "author": "Stephen Tamuno-opubo",
    "moddate": "2019-12-12T08:14:27+01:00",
    "source": "/app/processing_data/processing_data/pdf_documents/Jamb-Brochure.pdf",
    "total_pages": 1307,
    "page": 717,
    "page_label": "718"
  },
  "source": "Jamb-Brochure.pdf#page=718",
  "type": "pdf",
  "year": null
}