{
  "_id": "688371631eef35261f390a4f",
  "content_hash": "2fd8c26841a7b2bfd170b514df96a5e2",
  "collected_at": "2025-07-25T12:12:49.619418",
  "content": "1251 \n \nPROGRAMMES/COURSES AVAILABLE AT THE NIGERIA CERTIFICATE IN EDUCATION (NCE) LEVEL AND THE REQUIREMENTS FOR EACH \nCOURSE  \nCOLLEGE/COURSE  COURSE REQUIREMENTS  UTME SUBJECTS  \nTOPMOST  \n WAKABIU          \n WARRI-COE         \n ZUBA    \n  \n  \nINTEGRATED SCIENCE/PHYSICS  \n ADEYEMI        \n AGBOR              \nALVAN  \nANGEL  \nAKAMKPA  \n AKSCOE            \n ASSCOED       \nAZARE  \n BAMA                \nCOE-BILLIRI  \n DELAR         \n DUTSINMA       \n EKIADOLOR          \nESCE(T)  \n FC-AMUFU       \n FC-KANO        \n FC-KAT               \n FC-KONTA              \nFC-OBUDU      FC-\nOKENE         \n FC-PANK              \n FC-YOLA           \nFive (5) SSC credit passes in English Language, \nMathematics Physics and any two (2) Science \nsubjects  \n  \nPhysics and any other  two (2) Science subjects.",
  "file_info": {
    "filename": "Jamb-Brochure.pdf",
    "filepath": "/app/processing_data/processing_data/pdf_documents/Jamb-Brochure.pdf",
    "page_number": 1273,
    "total_pages": 1307,
    "file_size": 6544653
  },
  "metadata": {
    "producer": "Microsoft\u00ae Word 2016",
    "creator": "Microsoft\u00ae Word 2016",
    "creationdate": "2019-12-12T08:14:27+01:00",
    "author": "Stephen Tamuno-opubo",
    "moddate": "2019-12-12T08:14:27+01:00",
    "source": "/app/processing_data/processing_data/pdf_documents/Jamb-Brochure.pdf",
    "total_pages": 1307,
    "page": 1272,
    "page_label": "1273"
  },
  "source": "Jamb-Brochure.pdf#page=1273",
  "type": "pdf",
  "year": null
}