{
  "_id": "68837ff635e44bd06fe1625a",
  "content_hash": "333e91c4d253130756d04f6e540a0010",
  "collected_at": "2025-07-25T13:00:36.387848",
  "content": "6. A man wishes to keep some money in a savings \ndeposit at 25% compound interest so that after 3 \nyears he can buy a car for #150,000. how much does \n \n3 \nA. 2 B. \n1 \n 0 \nhe need to deposit now? -3  -2  -1 -1 \n-2 \n-3 \n1 2 3 \n \n7. If 31410 \u2013 2567 = 340x, find x \nA. 2n + 1 B. 2n \u2013 1 \nC. 4 D. \u00bc \n \n8. Audu bought an article for #50 000 and sold it to \nFemi at a loss of x%. Femi later sold the article to \nOche at a profit of 40%. If Femi made a profit of \n#10,000, find the value of x. \n \n \n \n \n \n18. \n \n \n \n \n \nFind the values of t for which the determinant of the \nA. 60 B. 50 matrix (t -4 0 0 ) \nC. 40 D. 20  (-1 t+t 1 ) is zero \n     ( 3 4 t-2) \n9. Simplify  3(2n + 1) \u2013 4(2n -1 )/2(n + 1) \u2013 2n \nA. 2n + 1 B. 2n - 1 \nC. 4 D. \u00bc \n \n10. If P3446 \u2013 23P26 = 2PP26, find the value of digit P. \nA. 2 B. 3 \n \nA. 0, 2, 3 B. \u20134, 2, 3 \nC. \u20134, -2, -3 D. 4, -2, 3 \n \n19. If (x - 1), (x + 1) and (x - 2) are factors of the \npolynomial ax3 + bx2 + cx \u2013 1, find a, b, c, respectively \n \n \n11. \n \n \nA. 8 B. 11/ \n \n \n20. A trader realizes 10x \u2013x2naira profit from the sale of \nC. 2/5 D. 1/8 \n \n12. A binary operation * is defined by a * b = ab. if a * 2 \n= 2 \u2013a, find the possible values of a. \nA. 1, -1 B. 1, 2 \nC. 2, -2 D. 1, -2 \n \n13. The 3rd term of an A. P. is 4x \u2013 2y and the 9th term i s  \n10x - 8y . find the common difference.  \nA. 19x  - 17y B. 8x - 4y \nC. x \u2013 y D. 2x \n \n14. Find the inverse of p under the binary operation * by \np * q= p + q \u2013 pq, where p and q are real numbers \nand zero is the identity. \nA. p B. p \u2013 1 \nC. p/p \u2013 1 D. p/p+1 \n \n(a, b) \n15. A matrix P(a, b) is such that PT= p, where  \n(c, d) \nPT is the transpose of P, if b = 1, then P is \nA. (0, 1) B. (0, 1) \n(1, 0) (-1, 0) \nx bags of corn. How many bags will give him the \nmaximum profit? \nA. 4 B. 5 \nC. 6 D. 7 \n \n21. Solve the inequality 2 \u2013 x > x2 \nA. x < -2 or x > 1 B. x > 2 or x < -1 \nC. \u20131 < x> 2 D. \u20132 < x < 1 \n \n22. If a and b are the roots of the equation 3x 2 + 5x \u2013 2 = \n0, find the value of 1/\uf061 + 1/\uf062 \nA. -5/2 B. \u20132/3 \nC. \u00bd D. 5/2 \n \n23. Find the minimum value of the function f(\uf071 ) = 2/3 \u2013 \ncos\uf071 for \uf06f \uf0a3 \uf071 \uf0a3 2\uf070. \nA. \u00bd B. 2/3 \nC. 1 D. 2 \n \n24. A frustum of a pyramid with square base has its upper \nand lower sections as squares of sizes 2m and 5m \nrespectively and the distance between them 6m. find \nthe height of the pyramid from which the frustum \nwas obtained.  \nC. (0, 1) D. (1, 1) A. 8.0m B. 8.4m \n (1, 1)  (-1,0) C. 9.0m D. 10.0m \n \n16. Evaluate (1/2 \u2013 \u00bc + 1/8 \u2013 1/16 + \u2026\u2026.) -1 \nA. 2/3 B. 0 \nC. \u20132/3 D. 1 \n25. P is a point on one side of the straight line UV and P \nmoves in the same direction as UV. If the straight \nline ST is on the locus of P and \uf0d0 VUS = 500, find \uf0d0 \nUST. \n17. The solution of the simultaneous inequalities 2x \u2013 2 A. 3100 B. 1300 \n \u00a3 y and 2y 2 \u00a3 x is represent by C. 800 D. 500 \n3 \n2 \n1 \n-3 -2 -1- 0 1 2 3 1 \n-2 \n-3 \nC. \n3 \n2 \n1 \n-3   -2 -1 0 1 2 3 -1 \n-2 \n-3 \nD. \n3 \n2 \n1 \n-3 -2 -1- 0 1 2 3 1 \n-2 \n-3 \n8 \nA. #112,000.50. B. #96,000.00 \nC. #85,714.28 D. #76,800.00 \n \nC. 4 D. 5 A. -1/2, 1, \u00bd B. \u00bd, 1, \u00bd \n    C. \u00bd, 1, -1/2 D. \u00bd, -1, \u00bd \nEvaluate 5-3log52 x 22log23",
  "file_info": {
    "filename": "JAMB Mathematics Past Questions 1983 - 2004.pdf",
    "filepath": "/app/processing_data/processing_data/pdf_documents/JAMB Mathematics Past Questions 1983 - 2004.pdf",
    "page_number": 52,
    "total_pages": 65,
    "file_size": 3098316
  },
  "metadata": {
    "producer": "Microsoft\u00ae Word for Office 365",
    "creator": "Microsoft\u00ae Word for Office 365",
    "creationdate": "2020-04-14T19:18:27+00:00",
    "moddate": "2020-04-14T19:18:27+00:00",
    "source": "/app/processing_data/processing_data/pdf_documents/JAMB Mathematics Past Questions 1983 - 2004.pdf",
    "total_pages": 65,
    "page": 51,
    "page_label": "52"
  },
  "source": "JAMB Mathematics Past Questions 1983 - 2004.pdf#page=52",
  "type": "pdf",
  "year": null
}