{
  "_id": "6883715d1eef35261f3906dd",
  "content_hash": "40edbfde6259d51597975be616a9da03",
  "collected_at": "2025-07-25T12:12:49.601135",
  "content": "498 \n \n BAUCHI        \nBAZE  \nBELLS  \n BENIN         \nBIU  \nCARITAS  \nCOOU  \n COVENANT      \n CRUTECH      \nDELSU  \nEDSU  \nEKSU  \nELIZADE  \n ESUTECH      \nFED-NDUFU  \nFED-OTUOKE  \nFED-OYE EKITI  \nFUNAAB  \n FUPRE         \n FUTA         \nFUTO with options in:  \na) Electronics/Computer  \nEngineering Tecnology  \nb) Power System Engineering  \nTechnology  \nc) Communication  \nEngineering Technology  \nd) Acoustic Engineering Tech.  \nGREGORY  \n   (vi)  \n(vii)  \n(viii) \n(ix)  \n(x)  \n(xi)  \n(xii)  \n(xiii)  \n(xiv)  \nEKSU accepts ND upper credit in Electrical Engineering \nand HND lower credit in Electrical Engineering.  \nESUTECH and BAUCHI accept ND/HND in relevant \nprogrammes with UTME requirements.  \nFED-OYE EKITI \u2013 Same as in Mechanical Engineering.  \nFUNAAB accepts `A' level passes in Mathematics, \nPhysics and Chemistry or equivalents. Accepts ND \nupper credit in Electrical/Electronic Engineering or \nrelevant programmes.  \nFUTA accepts ND upper credit or equivalent \nprofessional qualification in Electrical and Electronics \nEngineering in any related programmes or \u2018A\u2019 level \npasses or equivalents in Chemistry, Physics and \nMathematics.  \nFUTO requires at least two (2) \u2018A\u2019 level pa sses not \nbelow C in Mathematics and Physics or Chemistry.  \nAccepts ND/HND upper credit in Engineering.   \nCandidates must in addition meet UTME requirements.   \nDoes not accept first degree or NCE. \\IBADAN - As in \nAgricultural and Environmental Engineering.  \nILORIN - Same as Agricultural and Biosystem \nEngineering. Relevant Programmes include Electrical \nand/or Electronics Engineering Technology, Computer \nTechnology, Telecommunications or Communication \nEngineering, Power Systems Engineering, Control \nSystems Engi neering, Instrumentation Engineering, \nBiomedical Engineering.  \nJOS requires \u2018A\u2019 level or IJMB passes in Chemistry, \nPhysics and Mathematics. It also accepts ND (credit \nlevel) in Electrical/Electronics Engineering, Computer \nEngineering or a closely related p rogrammes from  \nrecognised institutions. Accepts \u2018O\u2019 level credit pass in \nMathematics.  \nLAUTECH accepts   \n \nCOURSE/DEGREE AWARDING \nINSTITUTIONS  \nREQUIREMENTS  \n  \n  \nUTME SUBJECTS  \n  \nSPECIAL CONSIDERATION (WAIVER) REMARKS  \nDIRECT ENTRY  UTME",
  "file_info": {
    "filename": "Jamb-Brochure.pdf",
    "filepath": "/app/processing_data/processing_data/pdf_documents/Jamb-Brochure.pdf",
    "page_number": 520,
    "total_pages": 1307,
    "file_size": 6544653
  },
  "metadata": {
    "producer": "Microsoft\u00ae Word 2016",
    "creator": "Microsoft\u00ae Word 2016",
    "creationdate": "2019-12-12T08:14:27+01:00",
    "author": "Stephen Tamuno-opubo",
    "moddate": "2019-12-12T08:14:27+01:00",
    "source": "/app/processing_data/processing_data/pdf_documents/Jamb-Brochure.pdf",
    "total_pages": 1307,
    "page": 519,
    "page_label": "520"
  },
  "source": "Jamb-Brochure.pdf#page=520",
  "type": "pdf",
  "year": null
}