{
  "_id": "68837f2435e44bd06fe140dd",
  "content_hash": "59255a9ffdb0df4d11f68b8cbc2d69eb",
  "collected_at": "2025-07-25T12:57:06.171606",
  "content": "C. 70 oC - 74oC D. 82 oC - 84oC \n \n6. The gas that gives brown colouration in brown ring \ntest is \nA. CO B. NO \nC. CO2 D. NO2 \n7. Which of the following gives a precipitate when treated \nwith NaOH solution? \nA. NH4Cl B. Na2CO3 \nC. AlCl3 E. CH3COONa \n \n8. The reaction of an alkene with hydrogen in the presence \nof a catalyst is \nA. a nucleophilic reaction \nB. an addition reaction \nC. a substitution reaction \nD. an oxidative reaction \n \n9. A rock sample was added to cold dilute HNO3. The gas \nevolved was passed into a solution of acidified K2Cr2O7 \nand the solution turned green. \nThe rock sample contains. \nA. SO 2- B. SO 2- \n15. The boiling of fat and aqueous caustic soda is referred to \nas. \nA. acidification B. hydrolysis  \nC. saponification D. esterification. \n \n16. Ordinary glass is manufactured from silica, CaCO3 and \nA. NaHCO3 B. K2SO4 \nC. K2CO3 D. Na2CO3 \n \n \n \n17. OH \n \nCH3- C-CH2-CH3 \nCH3 \nThe major product of the dehydration of the compound \nabove is \nA H \n \nCH3- C-CH2-CH3 \nCH \n4 3 \nC. NO3- D. Cl- \n \n10. The intermediate product formed when ethanol is \nprogressively oxidized to ethanoic acid with potassium \nheptaoxodichromate (V1) is \n3 \n \nB. CH3- C= CH2-CH3 \nCH3 \n \n \n \n \n \n \n \n \nThe compound above is a \nA. primary alkanols \nB. secondary alkanols \nC. tertiary alkanols \nD. glycol \n \n12, A red precipitate of copper (1) carbide is formed when \nammonium solution copper (1) chloride is introduced \ninto. \nA. CH3 - C =C -CH3 \nB. CH3  -CH2  -C a= CH3 \nC. CH2 =CH - CH2 CH3 \nD CH3CH2 CH2 CH3 \n13. The most important use of hydrogen is in the \nA. manufacture of methyl alcohol \nB. manufacture of ethyl alcohol \nC. hydrogenation of oils \nD. manufacture of ammonia \n \n14. Which of the following polymers is suitable for packaging \nand electrical insulation? \nA. Polyethene B. Polystyrene  \nC. Polyamide D. Polycarbonate. \n \n18. The number of isomers formed by C6H14 is \nA. 2 B. 3 \nC. 4 D. 5 \n \n19. Which of these pairs are synthetic and natural \nmacromolecules respectively? \nA. Nylon and polyethylene, creatine and \nhaemoglobin \nB. Nylon and creative, polyethylene and \nhaemoglobin \nC. Polyethylene and creatine, nylon and \nhaemoglobin \nD. Haemoglobin and nylon, creatine and \npolyethylene  \n \n20. An example of an element that can catenate is \nA. nitrogen B. chlorine \nC. carbon D. bromine \n \n \n21. Ethanol can easily be produced by \nA. distillation of starch solution \nB. catalyst oxidation of methane \nC. destructive distillation of wood \nD. fermentation of starch. \n A. methanal B. propanal  \nC. ethanal D. butanal C. CH3 - CH-CH-CH23 \n11. \n \nCH3 \nCH3  CH2--C-H \nOH \n   \n \nD. \nCH3 \nCH3 CH2CH2CH3 \nCH2",
  "file_info": {
    "filename": "JAMB Chemistry Past Question 1983 - 2004.pdf",
    "filepath": "/app/processing_data/processing_data/pdf_documents/JAMB Chemistry Past Question 1983 - 2004.pdf",
    "page_number": 64,
    "total_pages": 71,
    "file_size": 2350169
  },
  "metadata": {
    "producer": "Microsoft\u00ae Word for Office 365",
    "creator": "Microsoft\u00ae Word for Office 365",
    "creationdate": "2020-04-14T18:24:01+00:00",
    "moddate": "2020-04-14T18:24:01+00:00",
    "source": "/app/processing_data/processing_data/pdf_documents/JAMB Chemistry Past Question 1983 - 2004.pdf",
    "total_pages": 71,
    "page": 63,
    "page_label": "64"
  },
  "source": "JAMB Chemistry Past Question 1983 - 2004.pdf#page=64",
  "type": "pdf",
  "year": null
}