{
  "_id": "68837f5135e44bd06fe14b54",
  "content_hash": "61d5c6d2174e391722daa2727191919d",
  "collected_at": "2025-07-25T12:57:51.426654",
  "content": "A. Jerusalem B. Bethphage C. Nazareth D. \nBethany \n \n36. At the trials of Jesus, Pilate was perplexed because \nA. the Jews had no genuine case against Him \nB. Jesus gave no answer to the charges \nC. the Jews asked for the release of \nBarabbas, a notorious criminal \nD. he knew that Jesus had performed many \nmiracles among the Jews., \n \n37. Why did the accusers of Jesus stay behind while He \nwas led to the Praetorium? \nA. It was forbidden to follow the accused \nB. They were prevented from entering \nC. It was a Sabbath day \nD. They did not want to be defiled. \n \n38. Who was forced to carry the cross behind Jesus? \nA. Peter B. Joseph of Arimathea \nC. Andrew D. Simon of Cyrene, \n \n39. \u201cTruly I say to you, today you will be with me in Paradise\u201d. \nA. Zacchaeus  B.    the repentant robber \nC. the centurion D. Cleopas. \n \n40. According to Luke, the people who first got to Jesus\u2019 \ntomb were \nA. Mary the mother of Jesus, Peter and John \nB. Peter and Joanna \nC. Mary Magdalene and the other women \nD. Peter and John. \n41. Jesus Christ, the Good Shepherd was loved by the \nFather because He \nA. understood the needs of the sheep \nB. loved the sheep \nC. tended the sheep \nD. laid down His life for the sheep. \n \n42. Jesus said to her, \u201cI am the resurrection and the life: he \nwho believes in me, though he die, yet shall he live, \nand whoever lives and believes in me shall never die\u2026\u201d \nOn what occasion was this statement made? \nA. On the day of Jesus resurrection \nB. When Jesus demonstrated the fact of His \nresurrection to Thomas \nC. On the day Jesus restored Lazarus back \nto life \nD. When Jairus daughter was raised from the \ndead. \n43. According to Paul, if we give away all that we and we \ndeliver our bodies to be burnt, but have not love we \nA. are like a noisy gong \nB. are like a clanging cymbal \nC. gain only the world \nD. gain nothing \n \n44. \u201cNow the company of those who believed were of one \nhart and soul\u2026\u201d \nThis reveals that the early Christians \nA. had everything in common \nB. prayed together every hour \nC. celebrated the Holy Communion daily \nD. were always filled with the Holy Spirit. \n \n45. The suggestion to choose the seven deacons was made \nby  \nA. Paul   B.   Peter C. the twelve D. the church \n \n46. \u201cAnd in the last days it shall be, God declares, that I \nwill pour out my Spirit upon all flesh, and your sons \nand your daughters shall prophesy, and you\u2019re your \nmen shall see visions\u2026\u201dThis prophecy was fulfilled \nA. during the baptism of Jesus \nB. at Pentecost \nC. during the Transfiguration \nD. at His crucifixion. \n \n47. But you shall receive power when the Holy Spirit has \ncome upon you, and you shall be my witnesses in \nJerusalem and in all Judea and Samaria and to the end \nof the earth. \nThis statement commissions the apostles to \nA. establish the church in Jewish cities \nB. preach only to the Jews \nC. carry the gospel to all continents \nD. preach to the Gentiles in and outside Palestine \n \n48. Who was sent by God to restore Saul\u2019s sight after his \nencounter with Jesus on the road to Damasus? \nA. Simon B. Stephen C. Aeneas D. Ananias. \n \n49. \u201cSet apart for me Barnabas and Saul for the work to \nwhich I have called them \nThis statement was made by the \nA. Holy Spirit B. Church C. elders D. apostles. \n \n50. Following his encounter with the apostles, the 80 ruler \nof Cyprus \nA. dismissed them \nB. became blind for resisting the gospel \nC. requested that they choose another time to \npreach the gospel \nD. believed the gospel. \n \n  CHRISTIAN RELIGIOUS KNOWLEDGE 1994  \n \n \n1. When Elijah escaped to the brook Cherith, he was fed \nby  \nA. angels   B.    doves C. ravens D. sparrows, \n \n2. The contest on Mount Caronel was to prove that \nA. Baal was the god of Israel \nB. Baal controlled nature \nC. God was supreme to other gods  \nD. Israel had faith in God \n3. Naboth did not agree to release his vineyard to Ahab \nbecause  \nA. the amount offered for it was too small \nB. it was his major source of income \nC. it was his only vineyard \nD. it was the inheritance  of his fathers. \n \n4. What did Gehazi deceitful receive from Naaman? \nA. two talents of silver and two  festal garments \nB. two talents of silver and two shekels of gold",
  "file_info": {
    "filename": "JAMB CRK Past Question 1983 - 2004.pdf",
    "filepath": "/app/processing_data/processing_data/pdf_documents/JAMB CRK Past Question 1983 - 2004.pdf",
    "page_number": 32,
    "total_pages": 59,
    "file_size": 1517740
  },
  "metadata": {
    "producer": "Microsoft\u00ae Word for Office 365",
    "creator": "Microsoft\u00ae Word for Office 365",
    "creationdate": "2020-04-14T18:47:47+00:00",
    "moddate": "2020-04-14T18:47:47+00:00",
    "source": "/app/processing_data/processing_data/pdf_documents/JAMB CRK Past Question 1983 - 2004.pdf",
    "total_pages": 59,
    "page": 31,
    "page_label": "32"
  },
  "source": "JAMB CRK Past Question 1983 - 2004.pdf#page=32",
  "type": "pdf",
  "year": null
}