{
  "_id": "688371601eef35261f39081a",
  "content_hash": "6b646db0465d863a4af71d16c917d63e",
  "collected_at": "2025-07-25T12:14:16.542303",
  "content": "808 \n \nNOVENA  \n  \n   (xvi) GOUU same as in Political Science and International \nRelations.  \n(xvii) PAUL requires five (5) 'O' level credit passes at not more \nthan two (2) sittings including English Language, \nMathematics and three (3) Arts/Social Science subjects.  \n(xviii) BSU requires five (5) 'O' level credit passes from any Social \nScience or Arts subjects.  \n(xix) WESTERN-DEL same as in Political Science and Public \nAdministration.  \n(xx) JABU requires at least 'O' level pass in Mathematics.  \n(xxi) NDU requires five (5) 'O' level credit passes in English \nLanguage, Mathematics, Government or History and three \n(3) other subjects at not more than two (2) sittings.  \n(xxii) KWASU requires \u2018O\u2019 level credit passes in English Language, \nMathematics, Government and a ny two (2) other Social \nScience subjects.  \n(xxiii) ABUAD requires 'O' level credit passes in English language, \nMathematics, Government and any other two (2) Social \nScience subjects.  \n(xxiv) GOUU requires five (5) 'O' level credit passes to include \nEnglish Language, Mathematics, History or Government or \nEconomics and two (2) Science, Arts or Social Science \nsubjects.  \n(xxv) UMYUK requires five (5) 'O' level credit passes in English \nLanguage, Mathematics, and any two (2) Social Science \nsubjects and any other one (1) Arts subject a t not more \nthan two (2) sittings.  \n(xxvi) FED-OYE EKITI requires \u2018O\u2019 level credit pass in Mathematics \nand one (1) Science subject.  \n(xxvii) KSU requires \u2018O\u2019 level credit passes in Mathematics, English \nLanguage, Economics/Geography/Government and any \ntwo (2) other relevant subjects.  \n(xxviii) PHC requires  \u2018O\u2019 level credit passes in English Language, \nMathematics and any three (3) others from Social Science \nand Arts subjects.  \n(xxix) FED-DUTSINMA requires five (5) 'O' level credit passes in  \nGovernment or History/Civic Education, English, \nMathematics and any two (2) other subjects.  \n  \nUTME SUBJECTS",
  "file_info": {
    "filename": "Jamb-Brochure.pdf",
    "filepath": "/app/processing_data/processing_data/pdf_documents/Jamb-Brochure.pdf",
    "page_number": 830,
    "total_pages": 1307,
    "file_size": 6544653
  },
  "metadata": {
    "producer": "Microsoft\u00ae Word 2016",
    "creator": "Microsoft\u00ae Word 2016",
    "creationdate": "2019-12-12T08:14:27+01:00",
    "author": "Stephen Tamuno-opubo",
    "moddate": "2019-12-12T08:14:27+01:00",
    "source": "/app/processing_data/processing_data/pdf_documents/Jamb-Brochure.pdf",
    "total_pages": 1307,
    "page": 829,
    "page_label": "830"
  },
  "source": "Jamb-Brochure.pdf#page=830",
  "type": "pdf",
  "year": null
}