{
  "_id": "688371591eef35261f3904c1",
  "content_hash": "7bb278d242d7c244f3e07bd6053bc132",
  "collected_at": "2025-07-25T12:12:49.588672",
  "content": "36 \n \n1. UTME: Five (5)  credit passes in English Language  and Mathematics plus three (3) other subjects from the following: Chemistry,  Physics,  Economics, \nGeography, Technical Drawing and Fine   Arts, at not more than two (2) sittings in SSSC/WAEC, GCE, NECO, NABTEB or their equivalents.  \n  \n2. DIRECT ENTRY: 'A' level passes in any two (2) of the following: Mathematics, Economics, Geography, Physics and Biology OR ND at credit leve l obtained from a \nrecognized Polytechnic plus three (3) other SSC subjects passed at credit level.  \n  \nFACULTY OF MANAGEMENT AND SOCIAL SCIENCES  \n  \n A.     MANAGEMENT PROGRAMMES:  \n  \n1. UTME: Five (5) SSC credit passes in English Language, Mathematics and three (3) other subjects from Economics, Agricultural Science, Chemistry, Commerce and  \nGovernment are required for admission into Acco untancy, Banking and Finance, Business Administration, Public Administration, Industrial Relations and \nPersonnel Management and Marketing.  \n  \n2. DIRECT ENTRY: 'A' level passes in any two (2) of the following subjects: Mathematics, Economics, Government, and C ommerce OR ND at credit level obtained \nfrom a recognised Polytechnic plus three (3) other SSC subjects  passed at credit level.  \n  \n B.     SOCIAL SCIENCE AND ARTS PROGRAMMES:  \n1. UTME: Five (5) SSC passes at Credit Level in English Language, Mathematics and three (3) other subjects from Literature in Englis h, Economics, Government, \nBiology, Agricultural Science are required  for admission into English, Economics, Mass Communication, Political Science, Psychology and Sociology.  \n    \nEnglish and Mass Communication Programmes require credit passes in Literature in English while Economics Programme requires c redit pass in Economics at \nSSC.  \n2. DIRECT ENTRY: 'A' level passes in two (2) relevant Arts or Social Science subjects OR ND in relevant programmes at credit level plus three (3) other SSC subjects \npassed at credit level.  \n  \nFACULTY OF NATURAL SCIENCES  \n  \n1. UTME:  Five (5) passes at credit level in English Language and Mathematics plus three (3) other subjects from - Chemistry, Biology, Physics, Agricultural Science \nand Additional/Further Mathematics obtained at not more than two (2) sittings in WASSC, GCE, NECO, NABTEB or their equivalents are required for   admission \ninto Biochemistry, Computer Science, Industrial Chemistry, Information Technology, Microbiology,  Mathematics and Statistics.   \n  \n2. DIRECT ENTRY: 'A' level passes in any two (2) of the following: Mathematics, Biology, Chemistry, Physics. OR ND with credit pass from a rec ognised Polytechnic \nplus three (3) SSC subjects passed at credit level.  \n  \n 2.2.24  TAI SOLARIN UNIVERSITY OF EDUCATION,    IJEBU-ODE,",
  "file_info": {
    "filename": "Jamb-Brochure.pdf",
    "filepath": "/app/processing_data/processing_data/pdf_documents/Jamb-Brochure.pdf",
    "page_number": 58,
    "total_pages": 1307,
    "file_size": 6544653
  },
  "metadata": {
    "producer": "Microsoft\u00ae Word 2016",
    "creator": "Microsoft\u00ae Word 2016",
    "creationdate": "2019-12-12T08:14:27+01:00",
    "author": "Stephen Tamuno-opubo",
    "moddate": "2019-12-12T08:14:27+01:00",
    "source": "/app/processing_data/processing_data/pdf_documents/Jamb-Brochure.pdf",
    "total_pages": 1307,
    "page": 57,
    "page_label": "58"
  },
  "source": "Jamb-Brochure.pdf#page=58",
  "type": "pdf",
  "year": null
}