{
  "_id": "68837ff535e44bd06fe16224",
  "content_hash": "a91a29859d791ec624e27eb9183d33fe",
  "collected_at": "2025-07-25T13:00:36.387654",
  "content": "2 \n  Mathematics 1999  \n1. If (a2b3c)/a-1b4c5 \nWhat is the value of P + 2q? \nA. 5/2 B. \u20135/4 \n12. The first term of a geometrical progression is twice \nits common ratio. Find the sum of the first two terms \nof the progression if its sum to infinity is 8 \nC. \u201325/4 D. \u201310 A. 8/5 B. 8/3 \n    C. 72/25 D. 56/9 \n2. Find the value of x if \uf0d62/(x + \uf0d62) = 1/(x - \uf0d62) \nA. 3\uf0d62 + 4 B. 3\uf0d62 \u2013 4 \nC. 3 - 2\uf0d62 D. 4 + 2\uf0d62 \n \n3. A trader bought 100 oranges at 5 for #1.20,20 oranges \ngot spoilt and the remaining were sold at 4 for #1.50. \nfind the percentage gain or loss \nA. 30% gain B. 25% gain \nC. 30% loss D. 25% loss \n \n4. If U = {1, 2, 3, 4, 5, 6}, P = {3, 4, 5}, Q = {2, 4, 6} \nand R = {1, 2, 3 4}, list elements of (P\u00c8Q\u2019\u00c7R). \nA. {1, 2, 3, 4, 5, 6} B. {1, 2, 3, 4} \nC. {1} D. \u00c6 \n \n5. Divide 2434 6 by 426 \n \n13. Tope bought x oranges at #5.00 each and some \nmangoes at #4.00 each. If she bought twice as many \nmangoes as oranges and spent at least #and at most \n#, find the range of the value of x \nA. 4 \uf0a3 x \uf0a3 5 B. 5 \uf0a3 x \uf0a3 8 \nC. 5 \uf0a3 x \uf0a3 10 D. 8 \uf0a3 x \uf0a3 10 \n \n14. If m*n = m/n \u2013 n/m, for m,n E R, evaluate \u20133 *4 \nA. -25/12 B. \u20137/12 \nC. 7/12 D. 25/12 \n \n15. Find the matrix T if ST = I where S = (-1,  1) \n(1,  -2) \nand I is the identity matrix. \nA. 236 \nC. 526 \nB. 356 \nD. 556 \n9 9 5 9 \nA. 4 B. 3 \nC. 2 D. 1 \n \n7. Simplify \uf0d6(0.0023 x 750)/(0.00345) x 1.25 \nA. 15 B. 20 \nC. 40 D. 75 \n \n8. If log 10 = x, evaluate log 5 in terms of x. \n \n16. Divide 4x3 \u2013 3x + 1 by 2x - 1 \nA. 2x2 \u2013 x + 1 B. 2x2 \u2013 x \u2013 1 \nC. 2x2 + x + 1 D. 2x2 + x - 1 \n \n17. Three consecutive positive integers k, l and m are \nsuch that l2 = 3(k + m). find the value of m. \nA. 4 B. 5 \n8 8 \nA. 1/ x B. x \u2013 1/4 C. 6 D. 7 \nC. x \u2013 1/ D. x \u2013 1/ \n18.  \n9. A group of market women sell at least one of yam, \nplantain and maize. 12 of them sell maize, 10 sell \nyam and 14 sell plantain. 5 sell plantain and maize, 4 \nsell yam and maize, 2 sell yam and plantain only \nwhile 3 sell all the three items. How many women \nare in the group? \nThe shaded portion in the graph above is represented \nby \nA. 25 B. 19 \nC. 18 D. 17 \n \n10. Given that Q =  (6, 0) and   Q + P =  (7,  2) \n(4, 5) (6,  8) \nevaluate /Q + 2P/ \nA. 90 B. 96 \nC. 102 D. 120 \n \n11. A binary operation * is defined by a*b = ab + b for \nany real number a and b. if the identity element is \nzero, find the inverse of 2 under this operation  \nA. 2/3 B. \u00bd \nC. \u20131/2 D. 56/9 \nA. y + x \u2013 x3 0, y \u2013 x \u00a3 0 B. y - + x 3 \u00b3 0, y \u2013 x \u00a3 0 \nC. y + x \u2013 x3 \u00a3 0, y + x \u00b3 0 D. y \u2013 x + x3 \u00a3 0, y + x \u00a3 0 \n \n19. Factorize  completely  \nx2 + 2xy + y2 + 3x + 3y \u2013 18 \nA. (x + y + 6)(x + y - 3)   B. (x - y - 6)(x - y + 3) \nC. (x - y + 6)(x - y - 3) \n \n20. The sum of two members is twice their difference. If \nthe difference of the numbers is P, find the larger of \nthe two numbers.  \nA. p/2 B. 3p/2 \nC. 5p/2 D. 3p \n \n21. Express 1/x3 - 1 \nA. B. \n \nC. D. \ny \n45\nO\n \n-1 0 1 x \n3 2 \n C. (-1, -1) D. (-1, -1) \n6. If 2 x (Y3) = 3 (Y3) , find the value of Y  (01, -1)  (0, 1) \n \nA. (-2, 1) B. (-2, -1) \n (-1, 1)  (-1, -1)",
  "file_info": {
    "filename": "JAMB Mathematics Past Questions 1983 - 2004.pdf",
    "filepath": "/app/processing_data/processing_data/pdf_documents/JAMB Mathematics Past Questions 1983 - 2004.pdf",
    "page_number": 49,
    "total_pages": 65,
    "file_size": 3098316
  },
  "metadata": {
    "producer": "Microsoft\u00ae Word for Office 365",
    "creator": "Microsoft\u00ae Word for Office 365",
    "creationdate": "2020-04-14T19:18:27+00:00",
    "moddate": "2020-04-14T19:18:27+00:00",
    "source": "/app/processing_data/processing_data/pdf_documents/JAMB Mathematics Past Questions 1983 - 2004.pdf",
    "total_pages": 65,
    "page": 48,
    "page_label": "49"
  },
  "source": "JAMB Mathematics Past Questions 1983 - 2004.pdf#page=49",
  "type": "pdf",
  "year": null
}