{
  "_id": "68837f4f35e44bd06fe14908",
  "content_hash": "bbafcae5739374f5bf31dc2625f4cf19",
  "collected_at": "2025-07-25T12:57:51.425958",
  "content": "19. The prophet regularly addressed as \u2018son of man\u2019 was \nA. Jeremiah B. Ezekiel \nC. Isaiah D. Amos E. Hosea. \n \n20. What was the last miracle God performed before the \nIsraelites were released from Egypt? \nA. Thick darkness brought about by the hot wind \n\u2018Khamisin\u2019. \nB. The pollution of the Nile. \nC. The slaughter of all the male children. \nD. The plague of locusts. \nE. The slaughter of the first born. \n \n21. Who was the prophet who proved on Mount Carmel \nthat Yahweh is greater than Baal? \nA. Elijah B. Elisha \nC. Nathan D. Hosea \nE. Amos. \n \n22. On the third day of creation God made \nA. light. B. the firmament. \nC. the earth.  D.    animals. E. man. \n \n23. The Lord said to Moses: Cut two tablets of stone like \nthe first; and I will write upon the tablets the words that \nwere upon the first tablets which you broke. On what \noccasion was this said? \nA. At the renewal of the Covenant. \nB. During the election of Aaron. \nC. Just before the election of Joshua. \nD. After the first fall of Manna from heaven. \nE. Shortly before the conquest of Jericho. \n \n24. The city of Jericho was captured by the Israelites \nA. after a fierce battle lasting seven days. \nB. because the army of the city was betrayed by \nsome of its soldiers. \nC. because the defence system was very weak. \nD. at the blast of the trumpets of the  priests. \nE. because famine had broken out in the city and \nthe inhabitants surrendered because of \nhunger. \n \n25. The call of Isaiah took place \nA. on the return from the Babaylonian captivity. \nB. in the year of the death of King Uzziah. \nC. during the dedication of the temple by king \nSolomon. \nD. shortly before the rise of the Maccabees. \nE. after David had completely defeated the \nPhilistines. \n \n26. When Zechariah doubted the announcement of the \nbirth of John he \nA. fell down and fainted. \nB. was struck dumb. \nC. rebuked the angel Gabriel. \nD. knelt down and prayed. \nE. told his wife about it. \n \n27. Herod wanted to kill the child Jesus because \nA. he thought he would became a prophet. \nB. he learnt that he was born king of the Jews. \nC. the wise men worshipped Jesus. \nD. he was born of a virgin. \nE. he was born in a manger. \n28. What is the main lesson of the parable of the prodigal \nson? \nA. Parents must not be partial. \nB. A son should always obey his father. \nC. God forgives those who sincerely repent. \nD. One should not be wasteful. \nE. Brothers should love each other. \n \n29. \u2018These men who have turned the world upside down have \ncome here also, and Jason has received them. Which town \nis referred to here? \nA. Tarsus B. Ephesus \nC. Corinth D. Thessalonica E. Athens. \n \n30. \u2018And you, child, will be called the prophet of the Most \nHigh\u2019, refers to \nA. Samuel.  B. Jesus. C. Jeremiah. \nD. John the Baptist. E. Moses. \n \n31. The parable of the mustard seed teaches that \nA. the kingdom of God is invisible. \nB. although the kingdom of God is for all, very \nfew enter it. \nC. the kingdom of God will expand world-wide \nfrom what appears to be an insignificant \nbeginning. \nD. It is not certain when the kingdom of God will \ncome. \nE. The kingdom of God is within us. \n \n32. When the women got to the tomb of Jesus they found \nthe stone rolled away and \nA. saw Jesus coming out of the tomb. \nB. Jesus was no longer in the tomb. \nC. Jesus was sitting in the tomb. \nD. immediately saw a vision of Jesus. \nE. saw an angel singing hallelujah. \n \n33. \u2018You shall be my witnesses in Jerusalem and in all Judea \nand ... and to the end of the earth. \nA. Rome. B.    Antioch. C. Damascus. \nD. Samaria E. Israel. \n \n34. Paul was first arrested in Jerusalem because he \nA. brought Greeks into the temple. \nB. became a Christian. \nC. preached Christ in the temple. \nD. spoke against the temple. \nE. preached against circumcision. \n \n35. Which country in Africa provided Jesus with a refuge \nwhen Herod sought to destroy him? \nA. Algeria.  B.   Egypt. C. Morocco. \nD. Ethiopia. E. Libya. \n \n36. \u2018After me comes he who is mightier than I, the thong of \nwhose sandals I am not worthy to stoop down and \nuntie\u2019. Who said this? \nA. Jesus Christ. B. Mary Magdalene. \nC. Mark D. John the Baptist \nE. The annuciation angel. \n \n37. Who addressed Jesus at Jericho, saying, \u2018Jesus, son \nof David, have mercy on me?\u2019 \nA. Bartimaeus the blind beggar. \nB. Simon the leper. \nC. Simon of Cyrene.",
  "file_info": {
    "filename": "JAMB CRK Past Question 1983 - 2004.pdf",
    "filepath": "/app/processing_data/processing_data/pdf_documents/JAMB CRK Past Question 1983 - 2004.pdf",
    "page_number": 3,
    "total_pages": 59,
    "file_size": 1517740
  },
  "metadata": {
    "producer": "Microsoft\u00ae Word for Office 365",
    "creator": "Microsoft\u00ae Word for Office 365",
    "creationdate": "2020-04-14T18:47:47+00:00",
    "moddate": "2020-04-14T18:47:47+00:00",
    "source": "/app/processing_data/processing_data/pdf_documents/JAMB CRK Past Question 1983 - 2004.pdf",
    "total_pages": 59,
    "page": 2,
    "page_label": "3"
  },
  "source": "JAMB CRK Past Question 1983 - 2004.pdf#page=3",
  "type": "pdf",
  "year": null
}