{
  "_id": "6883715f1eef35261f39078f",
  "content_hash": "c6633d1c2663cc735b26f60f8f79bc59",
  "collected_at": "2025-07-25T12:14:16.539086",
  "content": "674 \n \nPROGRAMME/DEGREE  \nAWARDING INSTITUTIONS  \nREQUIREMENTS  \n  \n  \n  \n  \nUTME SUBJECTS  \nSPECIAL CONSIDERATION (WAIVER) REMARKS  \nDIRECT ENTRY  UTME  \nAQUACULTURE  \nCALEB              \n  \nAPPLIED ZOOLOGY  \nOOU                         \nBAUCHI               \n  \n  \nANIMAL BIOLOGY AND  \nENVIRONMENT  \nBENIN                \n  \nZOOLOGY AND  \nENVIRONMENTAL  BIOLOGY  \nUMUDIKE  \n  \n  \nANIMAL AND  \nENVIRONMENTAL  BIOLOGY  \nEDSU  \nEPU  \nFED-OYEEKITI  \nOSUMS  \n PHC    \n  \n  \n  \nCONSERVATION BIOLOGY  \nAUN              \n  \nENVRIONMENTAL SCIENCE \nAND TECHNOLOGY  \n   (ii) AAUA requires \u2018O\u2019 level credit pass in Chemistry as the fifth \n(5th) subject.  \n(iii) IMSU - As in Plant and Biotechnology. Requires \u2018O\u2019 level pass \nin Physics.  \n(iv) IGBINEDION requires 'O' level credit passes in English \nLanguage, Mathematics, Biology, Chemistry plus Physics or \nany other Science subject.  \n(v) UNN requires five (5)  'O' level credit passes obtained at not \nmore than two (2) sittings including Biology, Englis h \nLanguage, Mathematics or Physics and Chemistry  or its \nequivalent.  \n(vi) PHC requires Physics and Chemistry.  \n(vii) BAUCHI, BENIN and ILORIN require \u2018O\u2019 level credit passes in \nEnglish Language, Mathematics, Biology, Chemistry and \nPhysics. BENIN accepts \u2018O\u2019 level  c redit pass in any Science \nsubject in lieu of Physics.  \n(viii) OAU requires Physics or Chemistry.  \n(ix) CALABAR requires Chemistry, Biology, and Physics. \nUMUDIKE accepts \u2018O\u2019 level pass in English Language (x) \nMAIDUGURI accepts \u2018O\u2019 level pass in English Language with \n\u2018O\u2019 level credit pass in any of the  Sciences.  \n(xi) RSUST requires Chemistry.  \n(xii) DELSU accepts Health/Science in lieu of Biology and does \nnot require Mathematics.  \n(xiii) UMUDIKE same as in Botany.  \n(xiv) IMSU accepts \u2018O\u2019 level pass in English Language.  \n(xv) IBADAN requires five (5) or six (6)\u2019O\u2019 level credit passes at \none (1) or two (2) sittings to include, English Language, \nMathematics, Biology, Chemistry and any other Science \nsubject except Agricultural  Science.  \n(xvi) MAIDUGURI requires \u2018O\u2019 level   credit passes in Chemistry \nand Physics/Geography.  \n(xvii) UYO requires \u2018O\u2019 level credit passes in Mathematics and \nChemistry and may accept D7 in Physics.  \n(xviii) RENAISSANCE requires Geography.",
  "file_info": {
    "filename": "Jamb-Brochure.pdf",
    "filepath": "/app/processing_data/processing_data/pdf_documents/Jamb-Brochure.pdf",
    "page_number": 696,
    "total_pages": 1307,
    "file_size": 6544653
  },
  "metadata": {
    "producer": "Microsoft\u00ae Word 2016",
    "creator": "Microsoft\u00ae Word 2016",
    "creationdate": "2019-12-12T08:14:27+01:00",
    "author": "Stephen Tamuno-opubo",
    "moddate": "2019-12-12T08:14:27+01:00",
    "source": "/app/processing_data/processing_data/pdf_documents/Jamb-Brochure.pdf",
    "total_pages": 1307,
    "page": 695,
    "page_label": "696"
  },
  "source": "Jamb-Brochure.pdf#page=696",
  "type": "pdf",
  "year": null
}