{
  "_id": "6883715c1eef35261f3906a5",
  "content_hash": "e012ddf29b31b6c1a99a89b9ce37c36e",
  "collected_at": "2025-07-25T12:14:16.534995",
  "content": "445 \n \nCOURSE/DEGREE AWARDING \nINSTITUTIONS  \nREQUIREMENTS    \nUTME SUBJECTS  \nSPECIAL CONSIDERATION (WAIVER) REMARKS  \nDIRECT ENTRY  UTME  \n NSUGBE        \n OAU       \n OOU         \n OSCOE         \n PHC        \nTANSIAN  \n TASUED            \nUNN  \n UNIOSUN       \nUNIZIK  \n UYO        \nWARRI  \n  \n  \nEDUCATION AND GOVERNMENT  \nABSU  \n IMSU         \n  \n   (xii) UNIOSUN accepts two (2) \u2018A\u2019 level passes including \nGovernment and one (1) other Social Sciences or Arts \nsubject, or NCE credit in relevant subjects.  \n(xiii) NDU \u2013 Same as Vocational and Technical Education.  \n(xiv) AAUA accepts   \n(a) two  (2)  \u2018A\u2019  level  passes \n chosen  from  \nGovernment/History Economics or Geography.  \n(b) NCE merit in Government/History, Economics or \nGeography.  \n(c) ND credit inPublic Administration.  \n  \n  \n  \nUTME  \n(i) OOU accepts TC II merit/credit in English Language, \nMathematics and three (3) other subjects.  \n(ii) UYO, IMSU, CALABAR, EDALV, UNN, PHC and ABUJA \nrequire 'O' levelpass in Mathematics  \n(iii) OAU requires five (5) 'O\u2019 level credit passes which must \ninclude Government, English Language and  \nMathematics or five (5) TC II credit/merit which must \ninclude English Language, Mathematics History and \nSocial Studies.  \n    (iv)  IAUED, UNIOSUN and CALABAR do not accept History \nin lieu of Government.  \n    (v)  BENIN, DELSU, OOU and LASU require 'O' level credit \npass in Mathematics. BENIN requires any Social \nSciences subject.  \n    (vi)  PHC requires one (1) of Economics, Commerce or \nGeography/Physics.  \n    (v)  BIU, DELSU and LASU requires 'O' levelcredit pass in \nMathematics.  \n    (vi)  ABSU requires five (5) 'O' levelcredit passes to include \nEnglish Language, Government or History and any \nthree (3) subjects, and  'O' levelpass in Mathematics.",
  "file_info": {
    "filename": "Jamb-Brochure.pdf",
    "filepath": "/app/processing_data/processing_data/pdf_documents/Jamb-Brochure.pdf",
    "page_number": 467,
    "total_pages": 1307,
    "file_size": 6544653
  },
  "metadata": {
    "producer": "Microsoft\u00ae Word 2016",
    "creator": "Microsoft\u00ae Word 2016",
    "creationdate": "2019-12-12T08:14:27+01:00",
    "author": "Stephen Tamuno-opubo",
    "moddate": "2019-12-12T08:14:27+01:00",
    "source": "/app/processing_data/processing_data/pdf_documents/Jamb-Brochure.pdf",
    "total_pages": 1307,
    "page": 466,
    "page_label": "467"
  },
  "source": "Jamb-Brochure.pdf#page=467",
  "type": "pdf",
  "year": null
}