{
  "_id": "68837f6635e44bd06fe1523c",
  "content_hash": "f28d8690f80b36d0f7c091e7cca99b3a",
  "collected_at": "2025-07-25T12:58:13.940778",
  "content": "affect a business operation? \nA. Competition, industry and product \nB. Competition, labour and political \nC. Political, cultural and labour \nD. Economic, social and legal. \n48. The right of the public to protection against question \nable products and marketing practices is \nA. an economic aspect of the business \nB. a social responsibility of the business \nC. a legal aspect of the business \nD. a political aspect of the business. \n49. Which of the following group of countries are members \nof the Niger Basin Commission? \nA. The Republic of Guinea, Burkina Faso and Nigeria \nB. Ghana, Liberia and the Republic of Benin. \nC. Mali, Liberia and Nigeria. \nD. Ghana, Burkina Faso and Chad. \n50. The proposed monetary integration within ECOWAS \nsub- region has the overriding benefit of \nA. improved exchange B. enhanced trade \nC. enhanced development D. improved relations. \n \n  Commerce 2000  \n \n \n \n1. Government policies relating to the establishment and \noperations of businessess are targeted at \n \nA. even spread of facilities and employment \nB. the general improvement of the economy \nC. increasing the profits of business owners \nD. Diversification and expansion of businesses. \n \n2. The share capital value that forms part of the balance \nsheet total is the \n \nA. issued share capital \nB. called-up capital share capital \nC. authorised share capital \nD. paid-up share capital \n \n3. Bank overdraft as a short term source of fund is \n \nA. a current liability \nB. granted to a newly opened account \nC. repayable after more than a year \nD. an overdrawn account \n \n4. The measure of independence available to the individual \nbuisness units that come together is the main difference \nbetween \n \nA. vertical and horizontal integration \nB. merges and acquisitions \nC. trust and cartel \nD. consortium and amalgamation \n \n5. The major factors that facilitate merchadising are \n \nA. communication, advertising and banking \nB. Trading. Warehousing and production \nC. Banking, insurance and transportation \nD. Management, insurance and advertising \n \nUse the information below to answer questions 6 and 7 \n \nAmina Enterprises \nBalance Sheet as at 30/3/99 \nLiabilities N Assets N \nShare capital   400,000  Land 200,000 \nReserve fund 200,000   Buildings 150, 000 \nCreditors 110,000  Machinery 200,000 \nBills payable 50,000  Implements 20,000 \nUndistributed \nProfits 45,000 Office fittings 5,000 \nWages due 5,000 Raw materials 100,000 \nFinished goods 50,000 \nDebtors 20,000 \nBills receivable 15,000 \nCash at bank  45,000 \nCash at hand 5,000 \n \n6. What is the total fixed capital? \nA. N675,000 B. N575,000 \nC. N570,000 D. N550,000 \n \n7. Determine the circulating capital \nA. N250,000 B. N245,000 \nC. N235,000 D. N225,000 \n \n8. The term PLC implies that the shares are availble \nA. publicly on the stock exhange \nB. privately on the stock exchnage \nC. to the public at the comapny \nD. publicly in commercial banks \n \n9. The application of division of labour should generally \nbring about \nA. increase in  the variety of goods and services \nB. increase in the quantity of goods and services \nC. cheapness of goods and services \nD. cost effiiciency in the production of goods and \nservices \n \n \n10. On liquidation of a public limited liability company, the \nresidual owners are the \nA. Creditors B. debenture holders \nC. preference shareholders \nD. ordinary share holders",
  "file_info": {
    "filename": "JAMB Commerce Past Question 1994 - 2003.pdf",
    "filepath": "/app/processing_data/processing_data/pdf_documents/JAMB Commerce Past Question 1994 - 2003.pdf",
    "page_number": 15,
    "total_pages": 29,
    "file_size": 668275
  },
  "metadata": {
    "producer": "Microsoft\u00ae Word for Office 365",
    "creator": "Microsoft\u00ae Word for Office 365",
    "creationdate": "2020-04-14T18:41:27+00:00",
    "moddate": "2020-04-14T18:41:27+00:00",
    "source": "/app/processing_data/processing_data/pdf_documents/JAMB Commerce Past Question 1994 - 2003.pdf",
    "total_pages": 29,
    "page": 14,
    "page_label": "15"
  },
  "source": "JAMB Commerce Past Question 1994 - 2003.pdf#page=15",
  "type": "pdf",
  "year": null
}